ms_teams_files_connector/__init__.py
MSTeamsFilesConnector-1.0.3.dist-info/LICENSE
MSTeamsFilesConnector-1.0.3.dist-info/METADATA
MSTeamsFilesConnector-1.0.3.dist-info/WHEEL
MSTeamsFilesConnector-1.0.3.dist-info/top_level.txt
MSTeamsFilesConnector-1.0.3.dist-info/RECORD
