Metadata-Version: 2.1
Name: MSTeamsFilesConnector
Version: 1.0.3
Summary: A python package to simplify file uploads and downloads of MS Teams programetrically
Home-page: https://github.com/cctech-labs/ms-teams-files-connector
Author: Centre for Computational Technologies Pvt. Ltd. - CCTech
Author-email: info@cctech.co.in
Project-URL: Bug Tracker, https://github.com/cctech-labs/ms-teams-files-connector/issues
Project-URL: repository, https://github.com/cctech-labs/ms-teams-files-connector
Classifier: Programming Language :: Python :: 3
Classifier: License :: OSI Approved :: MIT License
Classifier: Operating System :: OS Independent
License-File: LICENSE
Requires-Dist: requests
